env_sender_pkg/__init__.py
env_sender_pkg/env_sender.py
env_sender-1.0.0.dist-info/METADATA
env_sender-1.0.0.dist-info/WHEEL
env_sender-1.0.0.dist-info/top_level.txt
env_sender-1.0.0.dist-info/RECORD
